README.md
setup.py
ak_useful_ml_distributions/Binomialdistribution.py
ak_useful_ml_distributions/Gaussiandistribution.py
ak_useful_ml_distributions/Generaldistribution.py
ak_useful_ml_distributions/__init__.py
ak_useful_ml_distributions.egg-info/PKG-INFO
ak_useful_ml_distributions.egg-info/SOURCES.txt
ak_useful_ml_distributions.egg-info/dependency_links.txt
ak_useful_ml_distributions.egg-info/not-zip-safe
ak_useful_ml_distributions.egg-info/top_level.txt