Metadata-Version: 2.1
Name: ak-useful-ml-distributions
Version: 1.5
Summary: Distribution Classes for Machine Learning
Home-page: UNKNOWN
Author: Andrew Kalil
Author-email: andrew_kalil@hotmail.com
License: UNKNOWN
Platform: UNKNOWN
